Neurix/__init__.py
Neurix/Classification/LogisticRegression.py
Neurix/Classification/__init__.py
Neurix/Regression/GDRidgeRegression.py
Neurix/Regression/LinearRegression.py
Neurix/Regression/OLSRidgeRegression.py
Neurix/Regression/__init__.py
Neurix/preprocessing/MaxAbsScaler.py
Neurix/preprocessing/MeanScaler.py
Neurix/preprocessing/MinMaxScaler.py
Neurix/preprocessing/SimpleImputer.py
Neurix/preprocessing/StandardScaler.py
Neurix/preprocessing/__init__.py
Neurix/relation/Pearson_corr.py
Neurix/relation/__init__.py
Neurix/relation/covariance.py
Neurix/score/__init__.py
Neurix/score/score.py
neurix-0.1.2.dist-info/METADATA
neurix-0.1.2.dist-info/WHEEL
neurix-0.1.2.dist-info/top_level.txt
neurix-0.1.2.dist-info/RECORD
