Metadata-Version: 2.4
Name: Neurix
Version: 0.1.2
Summary: Neurix is a simple ML utility library with preprocessing, regression, classification, and evaluation tools
Home-page: https://github.com/AvatanshuGupta/EasyML.git
Author: Avatanshu Gupta
Author-email: avatanshugupta@gmail.com
Classifier: Programming Language :: Python :: 3
Classifier: Operating System :: OS Independent
Requires-Python: >=3.8
Requires-Dist: numpy
Dynamic: author
Dynamic: author-email
Dynamic: classifier
Dynamic: description
Dynamic: description-content-type
Dynamic: home-page
Dynamic: requires-dist
Dynamic: requires-python
Dynamic: summary
